{"type": "Feature", "id": 12512277, "properties": {"woe:id": 12512277, "woe:parent_id": 12686761, "woe:name": "Yingchengzi Airport", "woe:placetype": 14, "woe:placetype_name": "Airport", "woe:lang": "ENG", "iso:country": "CN", "meta:provider": ["geoplanet:7.3.1", "geoplanet:7.3.2", "geoplanet:7.4.0", "geoplanet:7.4.1", "geoplanet:7.5.1", "geoplanet:7.5.2", "geoplanet:7.6.0", "geoplanet:7.8.1", "geoplanet:7.9.0", "geoplanet:7.10.0", "geoplanet:8.0.0", "woeplanet:8.0.0"], "meta:indexed": "2020-08-20T20:57:49.550776", "meta:updated": "2020-08-22T01:57:47.070002", "woe:hierarchy": {"continent": 24865671, "country": 23424781, "town": 0, "planet": 1, "county": 26198070, "suburb": 0, "state": 12578008, "region": 0, "localadmin": 12686761}, "woe:timezone_id": 56043597, "woe:hash": "wwymf8u3xv63", "woe:centroid": [121.405098, 38.983898], "geom:latitude": 38.983898, "geom:longitude": 121.405098, "geom:hash": "wwymf8u3xv63", "woe:latitude": 38.983898, "geom:centroid": [121.405098, 38.983898], "woe:longitude": 121.405098, "woe:repo": "woeplanet-airport-cn"}, "geometry": {"coordinates": [121.405098, 38.983898], "type": "Point"}}