{"type": "Feature", "id": 12512286, "properties": {"woe:id": 12512286, "woe:parent_id": 2156963, "woe:name": "Yulin Airport", "woe:placetype": 14, "woe:placetype_name": "Airport", "woe:lang": "ENG", "iso:country": "CN", "meta:provider": ["geoplanet:7.3.1", "geoplanet:7.3.2", "geoplanet:7.4.0", "geoplanet:7.4.1", "geoplanet:7.5.1", "geoplanet:7.5.2", "geoplanet:7.6.0", "geoplanet:7.8.1", "geoplanet:7.9.0", "geoplanet:7.10.0", "geoplanet:8.0.0", "woeplanet:8.0.0"], "meta:indexed": "2020-08-20T20:57:49.558578", "meta:updated": "2020-08-22T01:57:47.073636", "woe:hierarchy": {"continent": 24865671, "country": 23424781, "town": 0, "planet": 1, "county": 26198114, "suburb": 0, "state": 12578015, "region": 0, "localadmin": 12687244}, "woe:timezone_id": 56043593, "woe:hash": "wqy1cb5688q9", "woe:centroid": [109.768898, 38.276798], "geom:latitude": 38.276798, "geom:longitude": 109.768898, "geom:hash": "wqy1cb5688q9", "woe:latitude": 38.276798, "geom:centroid": [109.768898, 38.276798], "woe:longitude": 109.768898, "woe:repo": "woeplanet-airport-cn"}, "geometry": {"coordinates": [109.768898, 38.276798], "type": "Point"}}