{"type": "Feature", "id": 12512159, "geometry": {"type": "Point", "coordinates": [118.684601, 40.986]}, "properties": {"woe:id": 12512159, "woe:parent_id": 2171310, "woe:name": "Pingquan Airport", "woe:placetype": 14, "woe:placetype_name": "Airport", "woe:lang": "ENG", "iso:country": "CN", "meta:provider": ["geoplanet:7.3.1", "geoplanet:7.3.2", "geoplanet:7.4.0", "geoplanet:7.4.1", "geoplanet:7.5.1", "geoplanet:7.5.2", "geoplanet:7.6.0", "geoplanet:7.8.1", "geoplanet:7.9.0", "geoplanet:7.10.0", "geoplanet:8.0.0", "woeplanet:8.0.0"], "meta:indexed": "2020-08-20T20:57:49.444987", "meta:updated": "2020-10-14T11:51:20.724957", "woe:hierarchy": {"continent": 24865671, "country": 23424781, "town": 0, "planet": 1, "county": 26198253, "suburb": 0, "state": 12578000, "region": 0, "localadmin": 12686076}, "woe:timezone_id": 56043597, "woe:hash": "wxk3htr2z8ht", "woe:centroid": [118.684601, 40.986], "geom:latitude": 40.986, "geom:longitude": 118.684601, "geom:hash": "wxk3htr2z8ht", "woe:latitude": 40.986, "geom:centroid": [118.684601, 40.986], "woe:longitude": 118.684601, "woe:repo": "woeplanet-airport-cn", "geom:area": 0.0, "woe:scale": 19}}