{"type": "Feature", "id": 12512069, "geometry": {"type": "Point", "coordinates": [126.252403, 45.628101]}, "properties": {"woe:id": 12512069, "woe:parent_id": 12685806, "woe:name": "Harbin Yangjiagang Airport", "woe:placetype": 14, "woe:placetype_name": "Airport", "woe:lang": "ENG", "iso:country": "CN", "meta:provider": ["geoplanet:7.3.1", "geoplanet:7.3.2", "geoplanet:7.4.0", "geoplanet:7.4.1", "geoplanet:7.5.1", "geoplanet:7.5.2", "geoplanet:7.6.0", "geoplanet:7.8.1", "geoplanet:7.9.0", "geoplanet:7.10.0", "geoplanet:8.0.0", "woeplanet:8.0.0"], "meta:indexed": "2020-08-20T20:57:49.361851", "woe:alias_ENG_V": ["HRB Airport", "HRB", "Harbin Yangjiagang"], "meta:updated": "2020-10-14T11:51:20.626860", "woe:hierarchy": {"continent": 24865671, "country": 23424781, "town": 0, "planet": 1, "county": 26198257, "suburb": 0, "state": 12577998, "region": 0, "localadmin": 12685806}, "woe:timezone_id": 56043594, "woe:hash": "yb1g8fq4ynwb", "woe:centroid": [126.252403, 45.628101], "geom:latitude": 45.628101, "geom:longitude": 126.252403, "geom:hash": "yb1g8fq4ynwb", "woe:latitude": 45.628101, "geom:centroid": [126.252403, 45.628101], "woe:longitude": 126.252403, "woe:repo": "woeplanet-airport-cn", "geom:area": 0.0, "woe:scale": 19}}