{"type": "Feature", "id": 12512026, "geometry": {"type": "Point", "coordinates": [124.283096, 40.0242]}, "properties": {"woe:id": 12512026, "woe:parent_id": 2148008, "woe:name": "Dandong Airport", "woe:placetype": 14, "woe:placetype_name": "Airport", "woe:lang": "ENG", "iso:country": "CN", "meta:provider": ["geoplanet:7.3.1", "geoplanet:7.3.2", "geoplanet:7.4.0", "geoplanet:7.4.1", "geoplanet:7.5.1", "geoplanet:7.5.2", "geoplanet:7.6.0", "geoplanet:7.8.1", "geoplanet:7.9.0", "geoplanet:7.10.0", "geoplanet:8.0.0", "woeplanet:8.0.0"], "meta:indexed": "2020-08-20T20:57:49.321333", "woe:alias_ENG_V": ["DDG", "DDG Airport"], "meta:updated": "2020-10-14T11:51:20.649549", "woe:hierarchy": {"continent": 24865671, "country": 23424781, "town": 0, "planet": 1, "county": 26198226, "suburb": 0, "state": 12578008, "region": 0, "localadmin": 12686782}, "woe:timezone_id": 56043597, "woe:hash": "wz07snhjy59h", "woe:centroid": [124.283096, 40.0242], "geom:latitude": 40.0242, "geom:longitude": 124.283096, "geom:hash": "wz07snhjy59h", "woe:latitude": 40.0242, "geom:centroid": [124.283096, 40.0242], "woe:longitude": 124.283096, "woe:repo": "woeplanet-airport-cn", "geom:area": 0.0, "woe:scale": 19}}