{"type": "Feature", "id": 12512092, "geometry": {"type": "Point", "coordinates": [127.5047, 43.8209]}, "properties": {"woe:id": 12512092, "woe:parent_id": 12685646, "woe:name": "Jiaohe Airport", "woe:placetype": 14, "woe:placetype_name": "Airport", "woe:lang": "ENG", "iso:country": "CN", "meta:provider": ["geoplanet:7.3.1", "geoplanet:7.3.2", "geoplanet:7.4.0", "geoplanet:7.4.1", "geoplanet:7.5.1", "geoplanet:7.5.2", "geoplanet:7.6.0", "geoplanet:7.8.1", "geoplanet:7.9.0", "geoplanet:7.10.0", "geoplanet:8.0.0", "woeplanet:8.0.0"], "meta:indexed": "2020-08-20T20:57:49.383183", "meta:updated": "2020-10-14T11:51:20.625035", "woe:hierarchy": {"continent": 24865671, "country": 23424781, "town": 0, "planet": 1, "county": 26198064, "suburb": 0, "state": 12577995, "region": 0, "localadmin": 12685646}, "woe:timezone_id": 56043594, "woe:hash": "wzf9m3q54zg4", "woe:centroid": [127.5047, 43.8209], "geom:latitude": 43.8209, "geom:longitude": 127.5047, "geom:hash": "wzf9m3q54zg4", "woe:latitude": 43.8209, "geom:centroid": [127.5047, 43.8209], "woe:longitude": 127.5047, "woe:repo": "woeplanet-airport-cn", "geom:area": 0.0, "woe:scale": 19}}