{"type": "Feature", "id": 12511983, "geometry": {"type": "Point", "coordinates": [118.879997, 34.5504]}, "properties": {"woe:id": 12511983, "woe:parent_id": 12685559, "woe:name": "Baitabu Airport", "woe:placetype": 14, "woe:placetype_name": "Airport", "woe:lang": "ENG", "iso:country": "CN", "meta:provider": ["geoplanet:7.3.1", "geoplanet:7.3.2", "geoplanet:7.4.0", "geoplanet:7.4.1", "geoplanet:7.5.1", "geoplanet:7.5.2", "geoplanet:7.6.0", "geoplanet:7.8.1", "geoplanet:7.9.0", "geoplanet:7.10.0", "geoplanet:8.0.0", "woeplanet:8.0.0"], "meta:indexed": "2020-08-20T20:57:49.280217", "meta:updated": "2020-10-14T11:51:20.661800", "woe:hierarchy": {"continent": 24865671, "country": 23424781, "town": 0, "planet": 1, "county": 26198091, "suburb": 0, "state": 12577994, "region": 0, "localadmin": 12685559}, "woe:timezone_id": 56043597, "woe:hash": "wwhs91ty8tqe", "woe:centroid": [118.879997, 34.5504], "geom:latitude": 34.5504, "geom:longitude": 118.879997, "geom:hash": "wwhs91ty8tqe", "woe:latitude": 34.5504, "geom:centroid": [118.879997, 34.5504], "woe:longitude": 118.879997, "woe:repo": "woeplanet-airport-cn", "geom:area": 0.0, "woe:scale": 19}}