{"type": "Feature", "id": 12512146, "properties": {"woe:id": 12512146, "woe:parent_id": 12687244, "woe:name": "Mizhi Airport", "woe:placetype": 14, "woe:placetype_name": "Airport", "woe:lang": "ENG", "iso:country": "CN", "meta:provider": ["geoplanet:7.3.1", "geoplanet:7.3.2", "geoplanet:7.4.0", "geoplanet:7.4.1", "geoplanet:7.5.1", "geoplanet:7.5.2", "geoplanet:7.6.0", "geoplanet:7.8.1", "geoplanet:7.9.0", "geoplanet:7.10.0", "geoplanet:8.0.0", "woeplanet:8.0.0"], "meta:indexed": "2020-08-20T20:57:49.432390", "meta:updated": "2020-08-22T01:57:47.019698", "woe:hierarchy": {"continent": 24865671, "country": 23424781, "town": 0, "planet": 1, "county": 26198114, "suburb": 0, "state": 12578015, "region": 0, "localadmin": 12687244}, "woe:timezone_id": 56043593, "woe:hash": "wqwr88n04zg0", "woe:centroid": [110.069397, 37.880901], "geom:latitude": 37.880901, "geom:longitude": 110.069397, "geom:hash": "wqwr88n04zg0", "woe:latitude": 37.880901, "geom:centroid": [110.069397, 37.880901], "woe:longitude": 110.069397, "woe:repo": "woeplanet-airport-cn"}, "geometry": {"coordinates": [110.069397, 37.880901], "type": "Point"}}