{"type": "Feature", "id": 12512181, "geometry": {"type": "Point", "coordinates": [128.354507, 45.201099]}, "properties": {"woe:id": 12512181, "woe:parent_id": 12685843, "woe:name": "Shangzhi Airport", "woe:placetype": 14, "woe:placetype_name": "Airport", "woe:lang": "ENG", "iso:country": "CN", "meta:provider": ["geoplanet:7.3.1", "geoplanet:7.3.2", "geoplanet:7.4.0", "geoplanet:7.4.1", "geoplanet:7.5.1", "geoplanet:7.5.2", "geoplanet:7.6.0", "geoplanet:7.8.1", "geoplanet:7.9.0", "geoplanet:7.10.0", "geoplanet:8.0.0", "woeplanet:8.0.0"], "meta:indexed": "2020-08-20T20:57:49.466131", "meta:updated": "2020-10-14T11:51:20.750327", "woe:hierarchy": {"continent": 24865671, "country": 23424781, "town": 0, "planet": 1, "county": 26198257, "suburb": 0, "state": 12577998, "region": 0, "localadmin": 12685843}, "woe:timezone_id": 56043594, "woe:hash": "yb530u8gkz96", "woe:centroid": [128.354507, 45.201099], "geom:latitude": 45.201099, "geom:longitude": 128.354507, "geom:hash": "yb530u8gkz96", "woe:latitude": 45.201099, "geom:centroid": [128.354507, 45.201099], "woe:longitude": 128.354507, "woe:repo": "woeplanet-airport-cn", "geom:area": 0.0, "woe:scale": 19}}