{"type": "Feature", "id": 12512016, "geometry": {"type": "Point", "coordinates": [112.175797, 30.9489]}, "properties": {"woe:id": 12512016, "woe:parent_id": 12686279, "woe:name": "Ching-Men Airport", "woe:placetype": 14, "woe:placetype_name": "Airport", "woe:lang": "ENG", "iso:country": "CN", "meta:provider": ["geoplanet:7.3.1", "geoplanet:7.3.2", "geoplanet:7.4.0", "geoplanet:7.4.1", "geoplanet:7.5.1", "geoplanet:7.5.2", "geoplanet:7.6.0", "geoplanet:7.8.1", "geoplanet:7.9.0", "geoplanet:7.10.0", "geoplanet:8.0.0", "woeplanet:8.0.0"], "meta:indexed": "2020-08-20T20:57:49.312480", "meta:updated": "2020-10-14T11:51:20.647252", "woe:hierarchy": {"continent": 24865671, "country": 23424781, "town": 0, "planet": 1, "county": 26198268, "suburb": 0, "state": 12578002, "region": 0, "localadmin": 12686279}, "woe:timezone_id": 56043597, "woe:hash": "wmxb0d5fmt0e", "woe:centroid": [112.175797, 30.9489], "geom:latitude": 30.9489, "geom:longitude": 112.175797, "geom:hash": "wmxb0d5fmt0e", "woe:latitude": 30.9489, "geom:centroid": [112.175797, 30.9489], "woe:longitude": 112.175797, "woe:repo": "woeplanet-airport-cn", "geom:area": 0.0, "woe:scale": 19}}