{"type": "Feature", "id": 12512034, "geometry": {"type": "Point", "coordinates": [105.766296, 29.635799]}, "properties": {"woe:id": 12512034, "woe:parent_id": 2158542, "woe:name": "Dazu Airport", "woe:placetype": 14, "woe:placetype_name": "Airport", "woe:lang": "ENG", "iso:country": "CN", "meta:provider": ["geoplanet:7.3.1", "geoplanet:7.3.2", "geoplanet:7.4.0", "geoplanet:7.4.1", "geoplanet:7.5.1", "geoplanet:7.5.2", "geoplanet:7.6.0", "geoplanet:7.8.1", "geoplanet:7.9.0", "geoplanet:7.10.0", "geoplanet:8.0.0", "woeplanet:8.0.0"], "meta:indexed": "2020-08-20T20:57:49.328009", "meta:updated": "2020-10-14T11:51:20.629369", "woe:hierarchy": {"continent": 24865671, "country": 23424781, "town": 0, "planet": 1, "county": 26198378, "suburb": 0, "state": 20070171, "region": 0, "localadmin": 12687284}, "woe:timezone_id": 56043593, "woe:hash": "wm70wg09j367", "woe:centroid": [105.766296, 29.635799], "geom:latitude": 29.635799, "geom:longitude": 105.766296, "geom:hash": "wm70wg09j367", "woe:latitude": 29.635799, "geom:centroid": [105.766296, 29.635799], "woe:longitude": 105.766296, "woe:repo": "woeplanet-airport-cn", "geom:area": 0.0, "woe:scale": 19}}