{"type": "Feature", "id": 12512088, "properties": {"woe:id": 12512088, "woe:parent_id": 2139983, "woe:name": "Jiangluo Airport", "woe:placetype": 14, "woe:placetype_name": "Airport", "woe:lang": "ENG", "iso:country": "CN", "meta:provider": ["geoplanet:7.3.1", "geoplanet:7.3.2", "geoplanet:7.4.0", "geoplanet:7.4.1", "geoplanet:7.5.1", "geoplanet:7.5.2", "geoplanet:7.6.0", "geoplanet:7.8.1", "geoplanet:7.9.0", "geoplanet:7.10.0", "geoplanet:8.0.0", "woeplanet:8.0.0"], "meta:indexed": "2020-08-20T20:57:49.379052", "meta:updated": "2020-08-22T01:57:46.998454", "woe:hierarchy": {"continent": 24865671, "country": 23424781, "town": 0, "planet": 1, "county": 26198339, "suburb": 0, "state": 12577997, "region": 0, "localadmin": 12685735}, "woe:timezone_id": 56043597, "woe:hash": "wsexcnfe103b", "woe:centroid": [117.469299, 26.7124], "geom:latitude": 26.7124, "geom:longitude": 117.469299, "geom:hash": "wsexcnfe103b", "woe:latitude": 26.7124, "geom:centroid": [117.469299, 26.7124], "woe:longitude": 117.469299, "woe:repo": "woeplanet-airport-cn"}, "geometry": {"coordinates": [117.469299, 26.7124], "type": "Point"}}