{"type": "Feature", "id": 12512059, "geometry": {"type": "Point", "coordinates": [90.920197, 29.2941]}, "properties": {"woe:id": 12512059, "woe:parent_id": 2144793, "woe:name": "Gonggar Airport", "woe:placetype": 14, "woe:placetype_name": "Airport", "woe:lang": "ENG", "iso:country": "CN", "meta:provider": ["geoplanet:7.3.1", "geoplanet:7.3.2", "geoplanet:7.4.0", "geoplanet:7.4.1", "geoplanet:7.5.1", "geoplanet:7.5.2", "geoplanet:7.6.0", "geoplanet:7.8.1", "geoplanet:7.9.0", "geoplanet:7.10.0", "geoplanet:8.0.0", "woeplanet:8.0.0"], "meta:indexed": "2020-08-20T20:57:49.352201", "meta:updated": "2020-10-14T11:51:20.611368", "woe:hierarchy": {"continent": 24865671, "country": 23424781, "town": 0, "planet": 1, "county": 26198236, "suburb": 0, "state": 12578004, "region": 0, "localadmin": 12686442}, "woe:timezone_id": 56043597, "woe:hash": "wj0wsuy4d0h9", "woe:centroid": [90.920197, 29.2941], "geom:latitude": 29.2941, "geom:longitude": 90.920197, "geom:hash": "wj0wsuy4d0h9", "woe:latitude": 29.2941, "geom:centroid": [90.920197, 29.2941], "woe:longitude": 90.920197, "woe:repo": "woeplanet-airport-cn", "geom:area": 0.0, "woe:scale": 19}}