{"type": "Feature", "id": 12523350, "geometry": {"type": "Point", "coordinates": [120.839722, 32.015511]}, "properties": {"woe:id": 12523350, "woe:parent_id": 2137088, "woe:name": "Nantong Airport", "woe:placetype": 14, "woe:placetype_name": "Airport", "woe:lang": "ENG", "iso:country": "CN", "meta:provider": ["geoplanet:7.3.1", "geoplanet:7.3.2", "geoplanet:7.4.0", "geoplanet:7.4.1", "geoplanet:7.5.1", "geoplanet:7.5.2", "geoplanet:7.6.0", "geoplanet:7.8.1", "geoplanet:7.9.0", "geoplanet:7.10.0", "geoplanet:8.0.0", "woeplanet:8.0.0"], "meta:indexed": "2020-08-20T20:57:49.587789", "woe:alias_ENG_V": ["NTG Airport", "NTG"], "meta:updated": "2020-10-14T11:51:20.670031", "woe:hierarchy": {"continent": 24865671, "country": 23424781, "town": 0, "planet": 1, "county": 26198095, "suburb": 0, "state": 12577994, "region": 0, "localadmin": 12685592}, "woe:timezone_id": 56043597, "woe:hash": "wttyju0zceg6", "woe:centroid": [120.839722, 32.015511], "geom:latitude": 32.015511, "geom:longitude": 120.839722, "geom:hash": "wttyju0zceg6", "woe:latitude": 32.015511, "geom:centroid": [120.839722, 32.015511], "woe:longitude": 120.839722, "woe:repo": "woeplanet-airport-cn", "geom:area": 0.0, "woe:scale": 19}}