{"type": "Feature", "id": 12512298, "geometry": {"type": "Point", "coordinates": [109.682899, 27.4429]}, "properties": {"woe:id": 12512298, "woe:parent_id": 2142798, "woe:name": "Zhijiang Airport", "woe:placetype": 14, "woe:placetype_name": "Airport", "woe:lang": "ENG", "iso:country": "CN", "meta:provider": ["geoplanet:7.3.1", "geoplanet:7.3.2", "geoplanet:7.4.0", "geoplanet:7.4.1", "geoplanet:7.5.1", "geoplanet:7.5.2", "geoplanet:7.6.0", "geoplanet:7.8.1", "geoplanet:7.9.0", "geoplanet:7.10.0", "geoplanet:8.0.0", "woeplanet:8.0.0"], "meta:indexed": "2020-08-20T20:57:49.569151", "meta:updated": "2020-10-14T11:51:20.691689", "woe:hierarchy": {"continent": 24865671, "country": 23424781, "town": 0, "planet": 1, "county": 26198211, "suburb": 0, "state": 12578001, "region": 0, "localadmin": 12686247}, "woe:timezone_id": 56043597, "woe:hash": "wkvupgudkz35", "woe:centroid": [109.682899, 27.4429], "geom:latitude": 27.4429, "geom:longitude": 109.682899, "geom:hash": "wkvupgudkz35", "woe:latitude": 27.4429, "geom:centroid": [109.682899, 27.4429], "woe:longitude": 109.682899, "woe:repo": "woeplanet-airport-cn", "geom:area": 0.0, "woe:scale": 19}}