{"type": "Feature", "id": 12512100, "geometry": {"type": "Point", "coordinates": [116.347099, 35.286201]}, "properties": {"woe:id": 12512100, "woe:parent_id": 12687077, "woe:name": "Jining Airport", "woe:placetype": 14, "woe:placetype_name": "Airport", "woe:lang": "ENG", "iso:country": "CN", "meta:provider": ["geoplanet:7.3.1", "geoplanet:7.3.2", "geoplanet:7.4.0", "geoplanet:7.4.1", "geoplanet:7.5.1", "geoplanet:7.5.2", "geoplanet:7.6.0", "geoplanet:7.8.1", "geoplanet:7.9.0", "geoplanet:7.10.0", "geoplanet:8.0.0", "woeplanet:8.0.0"], "meta:indexed": "2020-08-20T20:57:49.391723", "meta:updated": "2020-10-14T11:51:20.743407", "woe:hierarchy": {"continent": 24865671, "country": 23424781, "town": 0, "planet": 1, "county": 26198300, "suburb": 0, "state": 12578014, "region": 0, "localadmin": 12687077}, "woe:timezone_id": 56043597, "woe:hash": "ww68xx9m5bsg", "woe:centroid": [116.347099, 35.286201], "geom:latitude": 35.286201, "geom:longitude": 116.347099, "geom:hash": "ww68xx9m5bsg", "woe:latitude": 35.286201, "geom:centroid": [116.347099, 35.286201], "woe:longitude": 116.347099, "woe:repo": "woeplanet-airport-cn", "geom:area": 0.0, "woe:scale": 19}}