{"type": "Feature", "id": 12512281, "properties": {"woe:id": 12512281, "woe:parent_id": 12686926, "woe:name": "Yongning Airport", "woe:placetype": 14, "woe:placetype_name": "Airport", "woe:lang": "ENG", "iso:country": "CN", "meta:provider": ["geoplanet:7.3.1", "geoplanet:7.3.2", "geoplanet:7.4.0", "geoplanet:7.4.1", "geoplanet:7.5.1", "geoplanet:7.5.2", "geoplanet:7.6.0", "geoplanet:7.8.1", "geoplanet:7.9.0", "geoplanet:7.10.0", "geoplanet:8.0.0", "woeplanet:8.0.0"], "meta:indexed": "2020-08-20T20:57:49.554421", "meta:updated": "2020-08-22T01:57:47.071636", "woe:hierarchy": {"continent": 24865671, "country": 23424781, "town": 0, "planet": 1, "county": 12686916, "suburb": 0, "state": 12578011, "region": 0, "localadmin": 12686926}, "woe:timezone_id": 56043597, "woe:hash": "wx4w6m2b5vj3", "woe:centroid": [116.1157, 40.502499], "geom:latitude": 40.502499, "geom:longitude": 116.1157, "geom:hash": "wx4w6m2b5vj3", "woe:latitude": 40.502499, "geom:centroid": [116.1157, 40.502499], "woe:longitude": 116.1157, "woe:repo": "woeplanet-airport-cn"}, "geometry": {"coordinates": [116.1157, 40.502499], "type": "Point"}}